flask_realtime_analytics/__init__.py
flask_realtime_analytics/flask_realtime_analytics.py
flask_realtime_analytics/templates/analytics.html
flask_realtimeanalytics-0.1.0.dist-info/licenses/LICENSE
tests/__init__.py
tests/test_flask_realtime_analytics.py
flask_realtimeanalytics-0.1.0.dist-info/METADATA
flask_realtimeanalytics-0.1.0.dist-info/WHEEL
flask_realtimeanalytics-0.1.0.dist-info/top_level.txt
flask_realtimeanalytics-0.1.0.dist-info/RECORD
