Metadata-Version: 2.4
Name: Flask-RealTimeAnalytics
Version: 0.1.0
Summary: A Flask extension for real-time analytics dashboards
Home-page: https://github.com/TonyRolfe/flask-realtime-analytics
Author: Tony Rolfe
Author-email: tony.rolfe@ibm.com
Project-URL: Homepage, https://github.com/TonyRolfe/flask-realtime-analytics
Project-URL: Documentation, https://flask-realtime-analytics.readthedocs.io
Project-URL: Repository, https://github.com/TonyRolfe/flask-realtime-analytics
Project-URL: Issues, https://github.com/TonyRolfe/flask-realtime-analytics/issues
Classifier: Programming Language :: Python :: 3
Classifier: Programming Language :: Python :: 3.6
Classifier: Programming Language :: Python :: 3.7
Classifier: Programming Language :: Python :: 3.8
Classifier: Programming Language :: Python :: 3.9
Classifier: Programming Language :: Python :: 3.10
Classifier: Programming Language :: Python :: 3.11
Classifier: Programming Language :: Python :: 3.12
Classifier: License :: OSI Approved :: MIT License
Classifier: Operating System :: OS Independent
Classifier: Framework :: Flask
Classifier: Intended Audience :: Developers
Classifier: Topic :: Software Development :: Libraries :: Python Modules
Requires-Python: >=3.6
License-File: LICENSE
Requires-Dist: Flask>=2.0.0
Requires-Dist: Flask-SocketIO>=5.3.0
Requires-Dist: python-socketio>=5.7.0
Requires-Dist: SQLAlchemy>=1.4.0
Dynamic: author
Dynamic: author-email
Dynamic: classifier
Dynamic: home-page
Dynamic: license-file
Dynamic: requires-python
Dynamic: summary
